{"cameraMode":{"drawMode":0,"name":"Shaded","section":"Shading Mode"},"sceneLighting":true,"audioPlay":false,"sceneViewState":{"showFog":true,"showMaterialUpdate":false,"showSkybox":true,"showFlares":true,"showImageEffects":true,"showParticleSystems":true},"in2DMode":false,"pivot":{"x":-1.2814178466796876,"y":-0.980842113494873,"z":-0.338592529296875},"rotation":{"x":-0.1060902550816536,"y":0.4642452299594879,"z":-0.056123897433280948,"w":-0.8775469064712524},"size":9.759361267089844,"orthographic":false}